regennexus_mcp/__init__.py
regennexus_mcp/__main__.py
regennexus_mcp/bridge.py
regennexus_mcp/config.py
regennexus_mcp/server.py
regennexus_mcp-0.1.1.dist-info/METADATA
regennexus_mcp-0.1.1.dist-info/WHEEL
regennexus_mcp-0.1.1.dist-info/entry_points.txt
regennexus_mcp-0.1.1.dist-info/licenses/LICENSE
regennexus_mcp-0.1.1.dist-info/RECORD
