Metadata-Version: 2.4
Name: regennexus-mcp
Version: 0.1.1
Summary: MCP server adapter for RegenNexus UAP - AI-controlled hardware
Project-URL: Homepage, https://github.com/ReGenNow/regennexus-mcp
Project-URL: Documentation, https://github.com/ReGenNow/regennexus-mcp#readme
Project-URL: Repository, https://github.com/ReGenNow/regennexus-mcp
Project-URL: Issues, https://github.com/ReGenNow/regennexus-mcp/issues
Author: ReGen Designs LLC
License-Expression: MIT
License-File: LICENSE
Keywords: ai,claude,hardware,iot,mcp,model-context-protocol,regennexus,robotics,uap
Classifier: Development Status :: 4 - Beta
Classifier: Intended Audience :: Developers
Classifier: License :: OSI Approved :: MIT License
Classifier: Operating System :: OS Independent
Classifier: Programming Language :: Python :: 3
Classifier: Programming Language :: Python :: 3.9
Classifier: Programming Language :: Python :: 3.10
Classifier: Programming Language :: Python :: 3.11
Classifier: Programming Language :: Python :: 3.12
Classifier: Topic :: Home Automation
Classifier: Topic :: Scientific/Engineering :: Interface Engine/Protocol Translator
Classifier: Topic :: Software Development :: Libraries :: Python Modules
Requires-Python: >=3.9
Requires-Dist: pydantic>=2.0.0
Provides-Extra: all
Requires-Dist: aiohttp>=3.8.0; extra == 'all'
Requires-Dist: python-dotenv>=1.0.0; extra == 'all'
Requires-Dist: regennexus>=0.3.0; extra == 'all'
Provides-Extra: dev
Requires-Dist: black>=23.0.0; extra == 'dev'
Requires-Dist: pytest-asyncio>=0.21.0; extra == 'dev'
Requires-Dist: pytest>=7.0.0; extra == 'dev'
Requires-Dist: ruff>=0.1.0; extra == 'dev'
Provides-Extra: local
Requires-Dist: regennexus>=0.3.0; extra == 'local'
Provides-Extra: remote
Requires-Dist: aiohttp>=3.8.0; extra == 'remote'
